<?xml version="1.0" encoding="UTF-8" ?>
<!DOCTYPE mapper PUBLIC "-//mybatis.org//DTD Mapper 3.0//EN" "http://mybatis.org/dtd/mybatis-3-mapper.dtd" >
<mapper namespace="org.campus.repository.LogMapper" >
  <resultMap id="BaseResultMap" type="org.campus.model.Log" >
    <!--
      WARNING - @mbggenerated
      This element is automatically generated by MyBatis Generator, do not modify.
      This element was generated on Sun Aug 09 23:25:01 CST 2015.
    -->
    <id column="UID" property="uid" jdbcType="VARCHAR" />
    <result column="Thread" property="thread" jdbcType="INTEGER" />
    <result column="Level" property="level" jdbcType="VARCHAR" />
    <result column="Message" property="message" jdbcType="VARCHAR" />
    <result column="CustomMessage" property="custommessage" jdbcType="VARCHAR" />
    <result column="Exception" property="exception" jdbcType="VARCHAR" />
    <result column="ClassName" property="classname" jdbcType="VARCHAR" />
    <result column="ModuleName" property="modulename" jdbcType="VARCHAR" />
    <result column="MehodName" property="mehodname" jdbcType="VARCHAR" />
    <result column="IsActive" property="isactive" jdbcType="INTEGER" />
    <result column="CreateBy" property="createby" jdbcType="VARCHAR" />
    <result column="Date" property="date" jdbcType="TIMESTAMP" />
    <result column="LogID" property="logid" jdbcType="VARCHAR" />
  </resultMap>
  <sql id="Base_Column_List" >
    <!--
      WARNING - @mbggenerated
      This element is automatically generated by MyBatis Generator, do not modify.
      This element was generated on Sun Aug 09 23:25:01 CST 2015.
    -->
    UID, Thread, Level, Message, CustomMessage, Exception, ClassName, ModuleName, MehodName, 
    IsActive, CreateBy, Date, LogID
  </sql>
  <select id="selectByPrimaryKey" resultMap="BaseResultMap" parameterType="java.lang.String" >
    <!--
      WARNING - @mbggenerated
      This element is automatically generated by MyBatis Generator, do not modify.
      This element was generated on Sun Aug 09 23:25:01 CST 2015.
    -->
    select 
    <include refid="Base_Column_List" />
    from tl_log
    where UID = #{uid,jdbcType=VARCHAR}
  </select>
  <delete id="deleteByPrimaryKey" parameterType="java.lang.String" >
    <!--
      WARNING - @mbggenerated
      This element is automatically generated by MyBatis Generator, do not modify.
      This element was generated on Sun Aug 09 23:25:01 CST 2015.
    -->
    delete from tl_log
    where UID = #{uid,jdbcType=VARCHAR}
  </delete>
  <insert id="insert" parameterType="org.campus.model.Log" >
    <!--
      WARNING - @mbggenerated
      This element is automatically generated by MyBatis Generator, do not modify.
      This element was generated on Sun Aug 09 23:25:01 CST 2015.
    -->
    insert into tl_log (UID, Thread, Level, 
      Message, CustomMessage, Exception, 
      ClassName, ModuleName, MehodName, 
      IsActive, CreateBy, Date, 
      LogID)
    values (#{uid,jdbcType=VARCHAR}, #{thread,jdbcType=INTEGER}, #{level,jdbcType=VARCHAR}, 
      #{message,jdbcType=VARCHAR}, #{custommessage,jdbcType=VARCHAR}, #{exception,jdbcType=VARCHAR}, 
      #{classname,jdbcType=VARCHAR}, #{modulename,jdbcType=VARCHAR}, #{mehodname,jdbcType=VARCHAR}, 
      #{isactive,jdbcType=INTEGER}, #{createby,jdbcType=VARCHAR}, #{date,jdbcType=TIMESTAMP}, 
      #{logid,jdbcType=VARCHAR})
  </insert>
  <insert id="insertSelective" parameterType="org.campus.model.Log" >
    <!--
      WARNING - @mbggenerated
      This element is automatically generated by MyBatis Generator, do not modify.
      This element was generated on Sun Aug 09 23:25:01 CST 2015.
    -->
    insert into tl_log
    <trim prefix="(" suffix=")" suffixOverrides="," >
      <if test="uid != null" >
        UID,
      </if>
      <if test="thread != null" >
        Thread,
      </if>
      <if test="level != null" >
        Level,
      </if>
      <if test="message != null" >
        Message,
      </if>
      <if test="custommessage != null" >
        CustomMessage,
      </if>
      <if test="exception != null" >
        Exception,
      </if>
      <if test="classname != null" >
        ClassName,
      </if>
      <if test="modulename != null" >
        ModuleName,
      </if>
      <if test="mehodname != null" >
        MehodName,
      </if>
      <if test="isactive != null" >
        IsActive,
      </if>
      <if test="createby != null" >
        CreateBy,
      </if>
      <if test="date != null" >
        Date,
      </if>
      <if test="logid != null" >
        LogID,
      </if>
    </trim>
    <trim prefix="values (" suffix=")" suffixOverrides="," >
      <if test="uid != null" >
        #{uid,jdbcType=VARCHAR},
      </if>
      <if test="thread != null" >
        #{thread,jdbcType=INTEGER},
      </if>
      <if test="level != null" >
        #{level,jdbcType=VARCHAR},
      </if>
      <if test="message != null" >
        #{message,jdbcType=VARCHAR},
      </if>
      <if test="custommessage != null" >
        #{custommessage,jdbcType=VARCHAR},
      </if>
      <if test="exception != null" >
        #{exception,jdbcType=VARCHAR},
      </if>
      <if test="classname != null" >
        #{classname,jdbcType=VARCHAR},
      </if>
      <if test="modulename != null" >
        #{modulename,jdbcType=VARCHAR},
      </if>
      <if test="mehodname != null" >
        #{mehodname,jdbcType=VARCHAR},
      </if>
      <if test="isactive != null" >
        #{isactive,jdbcType=INTEGER},
      </if>
      <if test="createby != null" >
        #{createby,jdbcType=VARCHAR},
      </if>
      <if test="date != null" >
        #{date,jdbcType=TIMESTAMP},
      </if>
      <if test="logid != null" >
        #{logid,jdbcType=VARCHAR},
      </if>
    </trim>
  </insert>
  <update id="updateByPrimaryKeySelective" parameterType="org.campus.model.Log" >
    <!--
      WARNING - @mbggenerated
      This element is automatically generated by MyBatis Generator, do not modify.
      This element was generated on Sun Aug 09 23:25:01 CST 2015.
    -->
    update tl_log
    <set >
      <if test="thread != null" >
        Thread = #{thread,jdbcType=INTEGER},
      </if>
      <if test="level != null" >
        Level = #{level,jdbcType=VARCHAR},
      </if>
      <if test="message != null" >
        Message = #{message,jdbcType=VARCHAR},
      </if>
      <if test="custommessage != null" >
        CustomMessage = #{custommessage,jdbcType=VARCHAR},
      </if>
      <if test="exception != null" >
        Exception = #{exception,jdbcType=VARCHAR},
      </if>
      <if test="classname != null" >
        ClassName = #{classname,jdbcType=VARCHAR},
      </if>
      <if test="modulename != null" >
        ModuleName = #{modulename,jdbcType=VARCHAR},
      </if>
      <if test="mehodname != null" >
        MehodName = #{mehodname,jdbcType=VARCHAR},
      </if>
      <if test="isactive != null" >
        IsActive = #{isactive,jdbcType=INTEGER},
      </if>
      <if test="createby != null" >
        CreateBy = #{createby,jdbcType=VARCHAR},
      </if>
      <if test="date != null" >
        Date = #{date,jdbcType=TIMESTAMP},
      </if>
      <if test="logid != null" >
        LogID = #{logid,jdbcType=VARCHAR},
      </if>
    </set>
    where UID = #{uid,jdbcType=VARCHAR}
  </update>
  <update id="updateByPrimaryKey" parameterType="org.campus.model.Log" >
    <!--
      WARNING - @mbggenerated
      This element is automatically generated by MyBatis Generator, do not modify.
      This element was generated on Sun Aug 09 23:25:01 CST 2015.
    -->
    update tl_log
    set Thread = #{thread,jdbcType=INTEGER},
      Level = #{level,jdbcType=VARCHAR},
      Message = #{message,jdbcType=VARCHAR},
      CustomMessage = #{custommessage,jdbcType=VARCHAR},
      Exception = #{exception,jdbcType=VARCHAR},
      ClassName = #{classname,jdbcType=VARCHAR},
      ModuleName = #{modulename,jdbcType=VARCHAR},
      MehodName = #{mehodname,jdbcType=VARCHAR},
      IsActive = #{isactive,jdbcType=INTEGER},
      CreateBy = #{createby,jdbcType=VARCHAR},
      Date = #{date,jdbcType=TIMESTAMP},
      LogID = #{logid,jdbcType=VARCHAR}
    where UID = #{uid,jdbcType=VARCHAR}
  </update>
</mapper>